relizene_weather/__init__.py
relizene_weather/api_call.py
relizene_weather/main.py
relizene_weather/settings/__init__.py
relizene_weather/settings/settings.py
relizene_weather/settings/validator.py
relizene_weather-1.0.1.dist-info/licenses/LICENSE
relizene_weather-1.0.1.dist-info/METADATA
relizene_weather-1.0.1.dist-info/WHEEL
relizene_weather-1.0.1.dist-info/top_level.txt
relizene_weather-1.0.1.dist-info/RECORD
