Metadata-Version: 2.4
Name: relizene-weather
Version: 1.0.1
Summary: Python weather module with city validation
Home-page: https://github.com/relizene/Relizene_weather
Author: Relizene
Author-email: vovaegorov689@gmail.com
License: MIT
Classifier: Programming Language :: Python :: 3
Classifier: License :: OSI Approved :: MIT License
Classifier: Operating System :: OS Independent
Requires-Python: >=3.8
License-File: LICENSE
Requires-Dist: requests>=2.25
Requires-Dist: geopy>=2.0
Dynamic: license-file
